adafruit_ina219.py
adafruit_circuitpython_ina219-3.5.0.dist-info/licenses/LICENSE
adafruit_circuitpython_ina219-3.5.0.dist-info/METADATA
adafruit_circuitpython_ina219-3.5.0.dist-info/WHEEL
adafruit_circuitpython_ina219-3.5.0.dist-info/top_level.txt
adafruit_circuitpython_ina219-3.5.0.dist-info/RECORD
