Metadata-Version: 2.4
Name: adafruit-circuitpython-ina219
Version: 3.5.0
Summary: CircuitPython library for INA219 high side DC current sensor.
Author-email: Adafruit Industries <circuitpython@adafruit.com>
License: MIT
Project-URL: Homepage, https://github.com/adafruit/Adafruit_CircuitPython_INA219
Keywords: adafruit,blinka,circuitpython,micropython,ina219,sensor,current,high,voltage,featherwing,breakout,hardware
Classifier: Intended Audience :: Developers
Classifier: Topic :: Software Development :: Libraries
Classifier: Topic :: Software Development :: Embedded Systems
Classifier: Topic :: System :: Hardware
Classifier: License :: OSI Approved :: MIT License
Classifier: Programming Language :: Python :: 3
License-File: LICENSE
Requires-Dist: Adafruit-Blinka
Requires-Dist: adafruit-circuitpython-register
Requires-Dist: adafruit-circuitpython-busdevice
Dynamic: license-file
